LICENSE
MANIFEST.in
README.rst
requirements.txt
setup.py
dogen/__init__.py
dogen/cli.py
dogen/errors.py
dogen/generator.py
dogen/plugin.py
dogen/template_helper.py
dogen/tools.py
dogen/version.py
dogen.egg-info/PKG-INFO
dogen.egg-info/SOURCES.txt
dogen.egg-info/dependency_links.txt
dogen.egg-info/entry_points.txt
dogen.egg-info/requires.txt
dogen.egg-info/top_level.txt
dogen/plugins/__init__.py
dogen/plugins/cct.py
dogen/plugins/dist_git.py
dogen/plugins/repo.py
dogen/plugins/rpm.py
dogen/schema/__init__.py
dogen/schema/kwalify_schema.yaml
dogen/templates/__init__.py
dogen/templates/template.jinja