Metadata-Version: 1.1
Name: dogen
Version: 2.4.3
Summary: Dockerfile generator tool
Home-page: https://github.com/jboss-dockerfiles/dogen
Author: Cloud Enablement
Author-email: cloud-enablement-feedback@redhat.com
License: MIT
Download-URL: https://github.com/jboss-dockerfiles/dogen/archive/2.4.3.tar.gz
Keywords: docker
Platform: UNKNOWN
